[
    {
      "title": "Bug Hunter",
      "content": "It worked locally!",
      "received": "2024-09-01"
    },
    {
      "title": "Stack Overflowed",
      "content": "Copied with pride.",
      "received": "2024-09-02"
    },
    {
      "title": "Commit Life",
      "content": "Fixes all bugs!",
      "received": "2024-09-03"
    },
    {
      "title": "404 Humor",
      "content": "Sleep not found.",
      "received": "2024-09-04"
    },
    {
      "title": "Debugger King",
      "content": "Blame the cache.",
      "received": "2024-09-05"
    }
  ]
  
